{
  "entrypoint": "src/index.html",
  "shell": "src/ui/testrtc-main.html",
  "fragments": [
    "src/ui/gum-dialog.html",
    "src/ui/gum-handler.html",
    "src/ui/line-chart.html",
    "src/ui/report-dialog.html",
    "src/ui/testrtc-suite.html",
    "src/ui/testrtc-test.html"
  ],
  "sources": [
   "src/js/*",
   "src/images/*",
   "src/css/*",
   "bower.json"
  ],
  "extraDependencies": [
    "components/*",
    "node_modules/webrtc-adapter/out/adapter.js",
    "app.yaml",
    "testrtc.py",
    "cron.yaml"
  ],
  "lint": {
    "rules": ["polymer-2-hybrid"]
  },
  "builds": [
    { "preset": "es5-bundled" },
    { "preset": "es6-unbundled" }
  ]
}
